{
  "border": "normal",
  "current_border_width": -1,
  "floating": "auto_off",
  "fullscreen_mode": 0,
  "geometry": {
    "x": 0,
    "y": 0,
    "width": 0,
    "height": 0
  },
  "layout": "splith",
  "marks": [],
  "name": "2:\uf269",
  "orientation": "horizontal",
  "percent": null,
  "scratchpad_state": "none",
  "sticky": false,
  "type": "workspace",
  "workspace_layout": "default",
  "nodes": [
    {
      "border": "pixel",
      "current_border_width": 0,
      "floating": "auto_off",
      "fullscreen_mode": 0,
      "geometry": {
        "x": 10,
        "y": 40,
        "width": 625,
        "height": 1010
      },
      "layout": "splith",
      "marks": [],
      "name": "image.png (PNG Image, 688\u00a0\u00d7\u00a0470 pixels) \u2014 Scaled (86%) \u2014 Firefox Nightly",
      "orientation": "none",
      "percent": 0.3333333333333333,
      "scratchpad_state": "none",
      "sticky": false,
      "type": "con",
      "workspace_layout": "default",
      "swallows": [
        {
          "class": "^firefox\\-nightly$",
          "instance": "^Navigator$",
          "title": "^image\\.png\\ \\(PNG\\ Image,\\ 688\u00a0\u00d7\u00a0470\\ pixels\\)\\ \u2014\\ Scaled\\ \\(86%\\)\\ \u2014\\ Firefox\\ Nightly$"
        }
      ]
    },
    {
      "border": "pixel",
      "current_border_width": 0,
      "floating": "auto_off",
      "fullscreen_mode": 0,
      "geometry": {
        "x": 645,
        "y": 40,
        "width": 630,
        "height": 1010
      },
      "layout": "splith",
      "marks": [],
      "name": "image.png (PNG Image, 1499\u00a0\u00d7\u00a0488 pixels) \u2014 Scaled (40%) \u2014 Firefox Nightly",
      "orientation": "none",
      "percent": 0.3333333333333333,
      "scratchpad_state": "none",
      "sticky": false,
      "type": "con",
      "workspace_layout": "default",
      "swallows": [
        {
          "class": "^firefox\\-nightly$",
          "instance": "^Navigator$",
          "title": "^image\\.png\\ \\(PNG\\ Image,\\ 1499\u00a0\u00d7\u00a0488\\ pixels\\)\\ \u2014\\ Scaled\\ \\(40%\\)\\ \u2014\\ Firefox\\ Nightly$"
        }
      ]
    },
    {
      "border": "pixel",
      "current_border_width": 0,
      "floating": "auto_off",
      "fullscreen_mode": 0,
      "geometry": {
        "x": 1285,
        "y": 40,
        "width": 625,
        "height": 1010
      },
      "layout": "splith",
      "marks": [],
      "name": "\u65b0\u898f\u30bf\u30d6 \u2014 Firefox Nightly",
      "orientation": "none",
      "percent": 0.3333333333333333,
      "scratchpad_state": "none",
      "sticky": false,
      "type": "con",
      "workspace_layout": "default",
      "swallows": [
        {
          "class": "^firefox\\-nightly$",
          "instance": "^Navigator$",
          "title": "^\u65b0\u898f\u30bf\u30d6\\ \u2014\\ Firefox\\ Nightly$"
        }
      ]
    }
  ]
}